naiwillcallyou/__init__.py
naiwillcallyou/entry.py
naiwillcallyou-2024.11.4.dist-info/LICENSE
naiwillcallyou-2024.11.4.dist-info/METADATA
naiwillcallyou-2024.11.4.dist-info/WHEEL
naiwillcallyou-2024.11.4.dist-info/entry_points.txt
naiwillcallyou-2024.11.4.dist-info/top_level.txt
naiwillcallyou-2024.11.4.dist-info/RECORD
